medtop/__init__.py
medtop/_nbdev.py
medtop/core.py
medtop/internal.py
medtop/preprocessing.py
medtop-0.0.8.dist-info/LICENSE
medtop-0.0.8.dist-info/METADATA
medtop-0.0.8.dist-info/WHEEL
medtop-0.0.8.dist-info/entry_points.txt
medtop-0.0.8.dist-info/top_level.txt
medtop-0.0.8.dist-info/RECORD
