Metadata-Version: 2.1
Name: medtop
Version: 0.0.8
Summary: https://amyolex.github.io/medtop/
Home-page: https://github.com/etfrenchvcu/medtop
Author: Amy Olex
Author-email: etfrench@vcu.edu
License: Apache Software License 2.0
Keywords: nlp
Platform: UNKNOWN
Classifier: Development Status :: 3 - Alpha
Classifier: Intended Audience :: Developers
Classifier: License :: OSI Approved :: Apache Software License
Classifier: Natural Language :: English
Classifier: Programming Language :: Python :: 3.6
Classifier: Programming Language :: Python :: 3.7
Classifier: Programming Language :: Python :: 3.8
Requires-Python: >=3.6
Requires-Dist: gensim
Requires-Dist: matplotlib
Requires-Dist: nltk
Requires-Dist: numpy
Requires-Dist: pandas
Requires-Dist: plotly
Requires-Dist: scipy
Requires-Dist: sklearn
Requires-Dist: textblob
Requires-Dist: umap-learn
